{
  "id": "monorepo-package-archive",
  "name": "monorepo-package-archive",
  "title": "设计 monorepo 包归档流程",
  "description": "",
  "status": "completed",
  "dev_type": null,
  "scope": null,
  "package": null,
  "priority": "P2",
  "creator": "mudssky",
  "assignee": "mudssky",
  "createdAt": "2026-07-12",
  "completedAt": "2026-07-12",
  "branch": null,
  "base_branch": "master",
  "worktree_path": null,
  "commit": null,
  "pr_url": null,
  "subtasks": [],
  "children": [],
  "parent": null,
  "relatedFiles": [],
  "notes": "",
  "meta": {}
}